voker/__init__.py
voker/client.py
voker/py.typed
voker-0.0.0.dist-info/METADATA
voker-0.0.0.dist-info/WHEEL
voker-0.0.0.dist-info/top_level.txt
voker-0.0.0.dist-info/RECORD
