Metadata-Version: 2.4
Name: voker
Version: 0.0.0
Summary: Add your description here
License-Expression: Apache-2.0
Requires-Python: >=3.14
Requires-Dist: httpx>=0.28.1
Requires-Dist: requests>=2.32.5
